llwp/LLWP.py
llwp/LLWP.svg
llwp/__init__.py
llwp-2.0.33.dist-info/licenses/LICENSE
llwp-2.0.33.dist-info/METADATA
llwp-2.0.33.dist-info/WHEEL
llwp-2.0.33.dist-info/entry_points.txt
llwp-2.0.33.dist-info/top_level.txt
llwp-2.0.33.dist-info/RECORD
