Metadata-Version: 2.4
Name: llwp
Version: 2.0.33
Summary: LLWP is a fast, efficient and easy solution for exploring and assigning spectra - relying on Loomis-Wood plots.
Author-email: Luis Bonah <bonah@ph1.uni-koeln.de>
Project-URL: Homepage, https://llwp.astro.uni-koeln.de/
Keywords: LLWP,Loomis-Wood Plots,Spectroscopy
Classifier: Programming Language :: Python :: 3
Classifier: License :: OSI Approved :: GNU General Public License v3 (GPLv3)
Classifier: Operating System :: OS Independent
Requires-Python: >=3.7
License-File: LICENSE
Requires-Dist: numpy
Requires-Dist: pandas
Requires-Dist: matplotlib
Requires-Dist: wrapt
Requires-Dist: pyckett>=0.1.28
Requires-Dist: scipy
Requires-Dist: PyQt6
Dynamic: license-file
